datashader/__init__.py
datashader/__main__.py
datashader/__version.py
datashader/_version.py
datashader/antialias.py
datashader/bundling.py
datashader/colors.py
datashader/compiler.py
datashader/composite.py
datashader/core.py
datashader/datatypes.py
datashader/layout.py
datashader/macros.py
datashader/mpl_ext.py
datashader/pipeline.py
datashader/reductions.py
datashader/resampling.py
datashader/tiles.py
datashader/utils.py
datashader/data_libraries/__init__.py
datashader/data_libraries/cudf.py
datashader/data_libraries/dask.py
datashader/data_libraries/dask_cudf.py
datashader/data_libraries/dask_xarray.py
datashader/data_libraries/pandas.py
datashader/data_libraries/xarray.py
datashader/datashape/__init__.py
datashader/datashape/coretypes.py
datashader/datashape/discovery.py
datashader/datashape/dispatch.py
datashader/datashape/error.py
datashader/datashape/internal_utils.py
datashader/datashape/lexer.py
datashader/datashape/parser.py
datashader/datashape/predicates.py
datashader/datashape/promote.py
datashader/datashape/type_symbol_table.py
datashader/datashape/typesets.py
datashader/datashape/user.py
datashader/datashape/validation.py
datashader/datashape/tests/__init__.py
datashader/datashape/tests/test_coretypes.py
datashader/datashape/tests/test_creation.py
datashader/datashape/tests/test_discovery.py
datashader/datashape/tests/test_lexer.py
datashader/datashape/tests/test_operations.py
datashader/datashape/tests/test_parser.py
datashader/datashape/tests/test_predicates.py
datashader/datashape/tests/test_promote.py
datashader/datashape/tests/test_str.py
datashader/datashape/tests/test_typeset.py
datashader/datashape/tests/test_user.py
datashader/datashape/tests/test_util.py
datashader/datashape/util/__init__.py
datashader/datashape/util/testing.py
datashader/datashape/util/tests/test_testing.py
datashader/examples/FAQ.ipynb
datashader/examples/README.md
datashader/examples/conftest.py
datashader/examples/datasets.yml
datashader/examples/environment.yml
datashader-0.18.2.dist-info/METADATA
datashader-0.18.2.dist-info/WHEEL
datashader-0.18.2.dist-info/entry_points.txt
datashader-0.18.2.dist-info/licenses/LICENSE.txt
datashader-0.18.2.dist-info/RECORD
