Metadata-Version: 2.4
Name: datashader
Version: 0.18.2
Summary: Data visualization toolchain based on aggregating into a grid
Project-URL: Homepage, https://datashader.org
Project-URL: Source, https://github.com/holoviz/datashader
Project-URL: HoloViz, https://holoviz.org/
Author-email: HoloViz developers <developers@holoviz.org>
Maintainer-email: HoloViz developers <developers@holoviz.org>
License: New BSD
License-File: LICENSE.txt
Classifier: Development Status :: 5 - Production/Stable
Classifier: Intended Audience :: Developers
Classifier: Intended Audience :: Science/Research
Classifier: License :: OSI Approved :: BSD License
Classifier: Natural Language :: English
Classifier: Operating System :: OS Independent
Classifier: Programming Language :: Python :: 3
Classifier: Programming Language :: Python :: 3.10
Classifier: Programming Language :: Python :: 3.11
Classifier: Programming Language :: Python :: 3.12
Classifier: Programming Language :: Python :: 3.13
Classifier: Topic :: Scientific/Engineering
Classifier: Topic :: Scientific/Engineering :: Visualization
Classifier: Topic :: Software Development :: Libraries
Requires-Python: >=3.10
Requires-Dist: colorcet
Requires-Dist: multipledispatch
Requires-Dist: numba
Requires-Dist: numpy
Requires-Dist: packaging
Requires-Dist: pandas
Requires-Dist: param
Requires-Dist: pyct
Requires-Dist: requests
Requires-Dist: scipy
Requires-Dist: toolz
Requires-Dist: xarray
Provides-Extra: tests
Requires-Dist: pytest; extra == 'tests'
